vitallens/__init__.py
vitallens/buffer.py
vitallens/client.py
vitallens/constants.py
vitallens/enums.py
vitallens/errors.py
vitallens/signal.py
vitallens/ssd.py
vitallens/utils.py
vitallens/methods/__init__.py
vitallens/methods/chrom.py
vitallens/methods/g.py
vitallens/methods/pos.py
vitallens/methods/rppg_method.py
vitallens/methods/simple_rppg_method.py
vitallens/methods/vitallens.py
vitallens/models/__init__.py
vitallens/models/Ultra-Light-Fast-Generic-Face-Detector-1MB/LICENSE
vitallens/models/Ultra-Light-Fast-Generic-Face-Detector-1MB/__init__.py
vitallens/models/Ultra-Light-Fast-Generic-Face-Detector-1MB/model_rfb_320.onnx
vitallens-0.5.1.dist-info/licenses/LICENSE
vitallens-0.5.1.dist-info/METADATA
vitallens-0.5.1.dist-info/WHEEL
vitallens-0.5.1.dist-info/top_level.txt
vitallens-0.5.1.dist-info/RECORD
