Metadata-Version: 2.4
Name: vitallens
Version: 0.5.1
Summary: Vital sign estimation from facial video
Author-email: Philipp Rouast <philipp@rouast.com>
License: MIT License
Project-URL: Repository, https://github.com/Rouast-Labs/vitallens-python.git
Project-URL: Issues, https://github.com/Rouast-Labs/vitallens-python/issues
Keywords: python,rppg,vital signs monitoring,heart rate,pulse,respiration
Classifier: Programming Language :: Python :: 3
Classifier: Operating System :: OS Independent
Classifier: License :: OSI Approved :: MIT License
Classifier: Development Status :: 4 - Beta
Requires-Python: >=3.10
License-File: LICENSE
Requires-Dist: importlib_resources>=5.12
Requires-Dist: numpy>=1.24
Requires-Dist: onnxruntime>=1.15.0
Requires-Dist: prpy[ffmpeg,numpy_min]>=0.3.12
Requires-Dist: python-dotenv>=1.0
Requires-Dist: pyyaml>=6.0.1
Requires-Dist: requests>=2.32.0
Provides-Extra: test
Requires-Dist: pytest; extra == "test"
Requires-Dist: flake8; extra == "test"
Dynamic: license-file
